shepherd_client/__init__.py
shepherd_client/cli.py
shepherd_client/client_admin.py
shepherd_client/client_user.py
shepherd_client/client_web.py
shepherd_client/config.py
shepherd_client/version.py
shepherd_client-2025.8.2.dist-info/METADATA
shepherd_client-2025.8.2.dist-info/WHEEL
shepherd_client-2025.8.2.dist-info/entry_points.txt
shepherd_client-2025.8.2.dist-info/top_level.txt
shepherd_client-2025.8.2.dist-info/zip-safe
shepherd_client-2025.8.2.dist-info/RECORD
