Metadata-Version: 2.4
Name: shepherd_client
Version: 2025.8.2
Summary: Web-Client for the Shepherd-Testbed
Author-email: Ingmar Splitt <ingmar.splitt@tu-dresden.de>
Maintainer-email: Ingmar Splitt <ingmar.splitt@tu-dresden.de>
Project-URL: Documentation, https://github.com/nes-lab/shepherd-webapi/blob/main/README.md
Project-URL: Issues, https://github.com/nes-lab/shepherd-webapi/issues
Project-URL: Source, https://github.com/nes-lab/shepherd-webapi
Keywords: testbed,beaglebone,pru,batteryless,energyharvesting,solar
Platform: unix
Platform: linux
Platform: osx
Platform: cygwin
Platform: win32
Platform: win64
Classifier: Development Status :: 5 - Production/Stable
Classifier: Intended Audience :: Developers
Classifier: Intended Audience :: Information Technology
Classifier: Intended Audience :: Science/Research
Classifier: Programming Language :: Python :: 3.10
Classifier: Programming Language :: Python :: 3.11
Classifier: Programming Language :: Python :: 3.12
Classifier: Programming Language :: Python :: 3.13
Classifier: License :: OSI Approved :: MIT License
Classifier: Operating System :: OS Independent
Classifier: Natural Language :: English
Requires-Python: >=3.10
Requires-Dist: requests
Requires-Dist: pydantic[email]>=2.11.5
Requires-Dist: shepherd_core>=2025.6.4
Requires-Dist: exrex
Requires-Dist: pyaml
Requires-Dist: typer
Requires-Dist: certifi>=2025.6.15
Provides-Extra: test
Requires-Dist: pytest; extra == "test"
Requires-Dist: pytest-click; extra == "test"
Requires-Dist: pytest-dependency; extra == "test"
Requires-Dist: pytest-timeout; extra == "test"
Requires-Dist: coverage; extra == "test"
Provides-Extra: all
Requires-Dist: shepherd-client[test]; extra == "all"
